flarefly/__init__.py
flarefly/custom_pdfs.py
flarefly/data_handler.py
flarefly/fitter.py
flarefly/pdf_builder.py
flarefly/pdf_configs.py
flarefly/utils.py
flarefly-0.0.15.dist-info/LICENSE
flarefly-0.0.15.dist-info/METADATA
flarefly-0.0.15.dist-info/WHEEL
flarefly-0.0.15.dist-info/entry_points.txt
flarefly-0.0.15.dist-info/top_level.txt
flarefly-0.0.15.dist-info/RECORD
