Metadata-Version: 2.1
Name: flarefly
Version: 0.0.15
Summary: FLexible And REliable Fitting LibrarY for particle physics analysis
Home-page: https://github.com/flarefly/flarefly
Author: flarefly-developers
Author-email: flarefly@googlegroups.com
License: GPL
Classifier: Development Status :: 3 - Alpha
Classifier: Intended Audience :: Education
Classifier: Intended Audience :: Developers
Classifier: Topic :: Scientific/Engineering :: Physics
Classifier: License :: OSI Approved :: GNU General Public License v3 (GPLv3)
Classifier: Programming Language :: Python :: 3.9
Classifier: Programming Language :: Python :: 3.10
Classifier: Programming Language :: Python :: 3.11
Requires-Python: >=3.9
License-File: LICENSE
Requires-Dist: psutil
Requires-Dist: dutil
Requires-Dist: prophet>=1.0.1
Requires-Dist: numpy<2.0.0
Requires-Dist: pandas>=2.2
Requires-Dist: uproot>=5.0
Requires-Dist: ipython>=7.16.1
Requires-Dist: jedi>=0.17.2
Requires-Dist: zfit<0.26.0
Requires-Dist: mplhep>=0.3.46
Requires-Dist: matplotlib>=3.9
Requires-Dist: pdg>=0.1.3
Requires-Dist: scipy>=1.13
Requires-Dist: hepstats>=0.8.1
Provides-Extra: dev
Requires-Dist: pylint>=2.6.2; extra == "dev"
Requires-Dist: flake8>=3.8.4; extra == "dev"
Requires-Dist: pytest>=6.2.2; extra == "dev"
Requires-Dist: twine>=3.3.0; extra == "dev"
Requires-Dist: setuptools>=53.0.0; extra == "dev"
Requires-Dist: wheel>=0.36.2; extra == "dev"
